AUTHORS.rst
CHANGES.rst
django_non_dark_admin/__init__.py
django_non_dark_admin/conf.py
django_non_dark_admin/static/django_non_dark_admin/no-dark-fix.css
django_non_dark_admin/templates/admin/base.html
django_non_dark_admin/templates/django_non_dark_admin/darkmode_switch.html
django_non_dark_admin/templatetags/admin_darkmode_switch.py
django_non_dark_admin-2.0.2.dist-info/LICENSE.rst
django_non_dark_admin-2.0.2.dist-info/WHEEL
django_non_dark_admin-2.0.2.dist-info/METADATA
django_non_dark_admin-2.0.2.dist-info/RECORD
