Metadata-Version: 2.1
Name: django-non-dark-admin
Version: 2.0.2
Summary: Disable dark mode in Django admin user interface in Django 3.2.x.
Home-page: https://github.com/DOOMer/django-non-dark-admin
License: BSD
Keywords: django,admin,dark,fix
Author: Artem Galichkin
Author-email: doomer3d@gmail.com
Maintainer: Artem Galichkin
Maintainer-email: doomer3d@gmail.com
Requires-Python: >=3.9,<4.0
Classifier: Development Status :: 5 - Production/Stable
Classifier: Environment :: Web Environment
Classifier: Framework :: Django
Classifier: License :: OSI Approved :: BSD License
Classifier: License :: Other/Proprietary License
Classifier: Operating System :: Unix
Classifier: Programming Language :: Python :: 3
Classifier: Programming Language :: Python :: 3.10
Classifier: Programming Language :: Python :: 3.2
Classifier: Programming Language :: Python :: 3.6
Classifier: Programming Language :: Python :: 3.9
Classifier: Topic :: Software Development :: Libraries :: Python Modules
Requires-Dist: django (>=3.2)
Project-URL: Bug Tracker, https://github.com/DOOMer/django-non-dark-admin/issues
Project-URL: Repository, https://github.com/DOOMer/django-non-dark-admin
